[
 {
  "docstatus": 0,
  "doctype": "Workflow State",
  "icon": "question-sign",
  "modified": "2023-01-31 16:00:34.742705",
  "name": "Pending",
  "style": "Warning",
  "workflow_state_name": "Pending"
 },
 {
  "docstatus": 0,
  "doctype": "Workflow State",
  "icon": "ok-sign",
  "modified": "2023-01-05 13:20:27.161030",
  "name": "Approved",
  "style": "Success",
  "workflow_state_name": "Approved"
 },
 {
  "docstatus": 0,
  "doctype": "Workflow State",
  "icon": "remove",
  "modified": "2023-01-05 13:20:27.164002",
  "name": "Rejected",
  "style": "Danger",
  "workflow_state_name": "Rejected"
 },
 {
  "docstatus": 0,
  "doctype": "Workflow State",
  "icon": "",
  "modified": "2023-01-31 15:56:51.070497",
  "name": "Payment Done",
  "style": "Success",
  "workflow_state_name": "Payment Done"
 }
]